[
  {
    "id": "jin-s2-001",
    "slug": "jin-s2-001-madara-uchiha",
    "setId": "jin-s2",
    "setSlug": "jin-s2",
    "number": "001",
    "name": "Madara Uchiha",
    "rarity": "R",
    "type": "Character",
    "character": "Madara Uchiha",
    "arc": "Sasuke Recovery",
    "image": "/images/cards/jin-s2-001.jpg",
    "description": "",
    "variant": null,
    "serialLimit": null,
    "isPromo": false,
    "characterSlug": "madara-uchiha"
  },
  {
    "id": "jin-s2-002",
    "slug": "jin-s2-002-naruto-uzumaki",
    "setId": "jin-s2",
    "setSlug": "jin-s2",
    "number": "002",
    "name": "Naruto Uzumaki",
    "rarity": "SR",
    "type": "Character",
    "character": "Naruto Uzumaki",
    "arc": "Kazekage Rescue",
    "image": "/images/cards/jin-s2-002.jpg",
    "description": "",
    "variant": null,
    "serialLimit": null,
    "isPromo": false,
    "characterSlug": "naruto-uzumaki"
  },
  {
    "id": "jin-s2-003",
    "slug": "jin-s2-003-sasuke-uchiha",
    "setId": "jin-s2",
    "setSlug": "jin-s2",
    "number": "003",
    "name": "Sasuke Uchiha",
    "rarity": "SSR",
    "type": "Character",
    "character": "Sasuke Uchiha",
    "arc": "Akatsuki Suppression",
    "image": "/images/cards/jin-s2-003.jpg",
    "description": "",
    "variant": null,
    "serialLimit": null,
    "isPromo": false,
    "characterSlug": "sasuke-uchiha"
  },
  {
    "id": "jin-s2-004",
    "slug": "jin-s2-004-sakura-haruno",
    "setId": "jin-s2",
    "setSlug": "jin-s2",
    "number": "004",
    "name": "Sakura Haruno",
    "rarity": "PTR",
    "type": "Character",
    "character": "Sakura Haruno",
    "arc": "Pain's Assault",
    "image": "/images/cards/jin-s2-004.jpg",
    "description": "",
    "variant": null,
    "serialLimit": null,
    "isPromo": false,
    "characterSlug": "sakura-haruno"
  },
  {
    "id": "jin-s2-005",
    "slug": "jin-s2-005-kakashi-hatake",
    "setId": "jin-s2",
    "setSlug": "jin-s2",
    "number": "005",
    "name": "Kakashi Hatake",
    "rarity": "UR",
    "type": "Jutsu",
    "character": "Kakashi Hatake",
    "arc": "Five Kage Summit",
    "image": "/images/cards/jin-s2-005.jpg",
    "description": "",
    "variant": null,
    "serialLimit": null,
    "isPromo": false,
    "characterSlug": "kakashi-hatake"
  },
  {
    "id": "jin-s2-006",
    "slug": "jin-s2-006-itachi-uchiha",
    "setId": "jin-s2",
    "setSlug": "jin-s2",
    "number": "006",
    "name": "Itachi Uchiha",
    "rarity": "PU",
    "type": "Jutsu",
    "character": "Itachi Uchiha",
    "arc": "Fourth Shinobi War",
    "image": "/images/cards/jin-s2-006.jpg",
    "description": "",
    "variant": null,
    "serialLimit": null,
    "isPromo": false,
    "characterSlug": "itachi-uchiha"
  },
  {
    "id": "jin-s2-007",
    "slug": "jin-s2-007-gaara",
    "setId": "jin-s2",
    "setSlug": "jin-s2",
    "number": "007",
    "name": "Gaara",
    "rarity": "MR",
    "type": "Weapon",
    "character": "Gaara",
    "arc": "The Last",
    "image": "/images/cards/jin-s2-007.jpg",
    "description": "",
    "variant": null,
    "serialLimit": null,
    "isPromo": false,
    "characterSlug": "gaara"
  },
  {
    "id": "jin-s2-008",
    "slug": "jin-s2-008-rock-lee",
    "setId": "jin-s2",
    "setSlug": "jin-s2",
    "number": "008",
    "name": "Rock Lee",
    "rarity": "BP",
    "type": "Scene",
    "character": "Rock Lee",
    "arc": "Land of Waves",
    "image": "/images/cards/jin-s2-008.jpg",
    "description": "",
    "variant": null,
    "serialLimit": null,
    "isPromo": false,
    "characterSlug": "rock-lee"
  }
]
